mcp_newsnow_server/__init__.py
mcp_newsnow_server/__main__.py
mcp_newsnow_server/cli.py
mcp_newsnow_server/server.py
mseep_mcp_newsnow-0.1.5.dist-info/METADATA
mseep_mcp_newsnow-0.1.5.dist-info/WHEEL
mseep_mcp_newsnow-0.1.5.dist-info/entry_points.txt
mseep_mcp_newsnow-0.1.5.dist-info/top_level.txt
mseep_mcp_newsnow-0.1.5.dist-info/RECORD
