Metadata-Version: 2.4
Name: mseep-mcp-newsnow
Version: 0.1.5
Summary: MCP server for multi-platform hottest news
Author-email: mseep <support@skydeck.ai>
Project-URL: Homepage, https://github.com/sligter/mcp_newsnow
Project-URL: Bug Tracker, https://github.com/sligter/mcp_newsnow/issues
Classifier: Programming Language :: Python :: 3
Classifier: Programming Language :: Python :: 3.10
Classifier: Programming Language :: Python :: 3.11
Classifier: License :: OSI Approved :: MIT License
Classifier: Operating System :: OS Independent
Requires-Python: >=3.10
Requires-Dist: mcp>=1.0.0
Requires-Dist: httpx>=0.25.0
